AllureReportLibrary/AllureListener.py
AllureReportLibrary/AllureReportLibrary.py
AllureReportLibrary/__init__.py
AllureReportLibrary/common.py
AllureReportLibrary/constant.py
AllureReportLibrary/constants.py
AllureReportLibrary/rules.py
AllureReportLibrary/structure.py
AllureReportLibrary/utils.py
AllureReportLibrary/version.py
robotframework_allurereport_zajic-1.3.0.dist-info/DESCRIPTION.rst
robotframework_allurereport_zajic-1.3.0.dist-info/METADATA
robotframework_allurereport_zajic-1.3.0.dist-info/RECORD
robotframework_allurereport_zajic-1.3.0.dist-info/WHEEL
robotframework_allurereport_zajic-1.3.0.dist-info/metadata.json
robotframework_allurereport_zajic-1.3.0.dist-info/top_level.txt
